setup.py
message_server.egg-info/PKG-INFO
message_server.egg-info/SOURCES.txt
message_server.egg-info/dependency_links.txt
message_server.egg-info/requires.txt
message_server.egg-info/top_level.txt
server/__init__.py
server/server.py
server/start_server.py
server/descriptors/__init__.py
server/descriptors/server_descriptor.py
server/gui_server/__init__.py
server/gui_server/main.py
server/gui_server/server.py
server/gui_server/users_list.py
server/jim/__init__.py
server/jim/error.py
server/jim/settings.py
server/jim/utils.py
server/metaclasses/__init__.py
server/metaclasses/server_meta.py