Metadata-Version: 1.0
Name: message-server
Version: 0.0.1
Summary: message_server
Home-page: UNKNOWN
Author: Oleg
Author-email: test.test@test.com
License: UNKNOWN
Platform: UNKNOWN
